[
  {
    "name": "Winter Days with Pasha Asinov",
    "file": "img/Winter Days with Pasha Asinov.png",
    "video_link": "https://player.vimeo.com/video/120838068",
    "description": "Predator's Teenage Son"
  },
  {
    "name": "SkyDive The Ranch.png",
    "file": "img/SkyDive The Ranch.png",
    "video_link": "https://player.vimeo.com/video/35234437",
    "description": "Predator's Teenage Son"
  },
  {
    "name": "Boat Party NYC",
    "file": "img/Boat Party NYC.png",
    "video_link": "https://player.vimeo.com/video/50988467",
    "description": "Predator's Teenage Son"
  },
  {
    "name": "Gleb & Anton 2011",
    "file": "img/Gleb & Anton 2011.png",
    "video_link": "https://player.vimeo.com/video/29512007",
    "description": "Predator's Teenage Son"
  }
]